psychxr/__init__.pxd
psychxr/__init__.py
psychxr/libovr/__init__.pxd
psychxr/libovr/__init__.py
psychxr/libovr/_libovr.cp36-win_amd64.pyd
psychxr/libovr/_libovr.cpp
psychxr/libovr/_libovr.pyx
psychxr/libovr/libovr_capi.pxd
psychxr/libovr/libovr_math.pxd
psychxr/ovr/__init__.pxd
psychxr/ovr/__init__.py
psychxr/ovr/capi.cp36-win_amd64.pyd
psychxr/ovr/capi.cpp
psychxr/ovr/capi.pyx
psychxr/ovr/math.cp36-win_amd64.pyd
psychxr/ovr/math.cpp
psychxr/ovr/math.pxd
psychxr/ovr/math.pyx
psychxr/ovr/ovr_capi.pxd
psychxr/ovr/ovr_capi_gl.pxd
psychxr/ovr/ovr_capi_util.pxd
psychxr/ovr/ovr_errorcode.pxd
psychxr/ovr/ovr_math.pxd
psychxr-0.2.2.dist-info/LICENSE
psychxr-0.2.2.dist-info/METADATA
psychxr-0.2.2.dist-info/WHEEL
psychxr-0.2.2.dist-info/top_level.txt
psychxr-0.2.2.dist-info/RECORD
