Metadata-Version: 2.1
Name: psychxr
Version: 0.2.2
Summary: Python extension library for interacting with eXtended Reality displays (HMDs), intended for research in neuroscience and psychology.
Home-page: http://psychxr.org
Author: Matthew D. Cutone, Laurie M. Wilcox
Author-email: cutonem@yorku.ca
Maintainer: Matthew D. Cutone
Maintainer-email: cutonem@yorku.ca
License: MIT
Platform: UNKNOWN
Classifier: Development Status :: 5 - Production/Stable
Classifier: Operating System :: Microsoft :: Windows :: Windows 10
Classifier: Operating System :: Microsoft :: Windows :: Windows 8.1
Classifier: Operating System :: Microsoft :: Windows :: Windows 7
Classifier: License :: OSI Approved :: MIT License
Classifier: Programming Language :: Python :: 3.6
Classifier: Programming Language :: Cython
Classifier: Intended Audience :: Science/Research
Requires-Dist: Cython (>=0.29.3)
Requires-Dist: numpy (>=1.13.3)
